sa_decor/__init__.py
sa_decor/engine.py
sa_decor/globals.py
sa_decor/session.py
sa_decor-1.0.1.dist-info/LICENSE.txt
sa_decor-1.0.1.dist-info/METADATA
sa_decor-1.0.1.dist-info/WHEEL
sa_decor-1.0.1.dist-info/top_level.txt
sa_decor-1.0.1.dist-info/RECORD
