Metadata-Version: 2.1
Name: sa-decor
Version: 1.0.1
Summary: SQLAlchemy decorators for an optional connection/session dependency injection.
Home-page: https://github.com/uhlikfil/sa_decor
Author: Filip Uhlík
Author-email: filipfilauhlik@gmail.com
Project-URL: Bug Tracker, https://github.com/uhlikfil/sa_decor/issues
Classifier: Programming Language :: Python :: 3
Classifier: License :: OSI Approved :: MIT License
Classifier: Operating System :: OS Independent
Requires-Python: >=3.7
License-File: LICENSE.txt
